{"xmlName":"TxnDisplayAddRq","xmlNameHtml":"TxnDisplayAdd.html",
 "xmlType":"Aggregate",
 "fcName":"ITxnDisplayAdd","fcNameHtml":"TxnDisplayAdd.html",
 "fcType":"nothing",
 "minVerUS":"3",
 "supports":{"US":true,"CA":true,"UK":true,"AU":true,"OE":false},
 "required":false,
 "elements":[
    {"xmlName":"TxnDisplayAddType","xmlNameHtml":"TxnDisplayAddType.html",
     "xmlType":"ENUMTYPE","xmlTypeHtml":"ENUMTYPE.html",
     "xmlEnumValues":["Bill","BillPayment","BuildAssembly","Charge","Check","CreditCardCharge","CreditCardCredit","CreditMemo","Deposit","Estimate","InventoryAdjustment","Invoice","ItemReceipt","JournalEntry","PurchaseOrder","ReceivePayment","SalesOrder","SalesReceipt","SalesTaxPaymentCheck","VendorCredit"],
     "fcName":"TxnDisplayAddType","fcNameHtml":"QBFC-TxnDisplayAddType.html",
     "fcType":"IQBENTxnDisplayAddTypeType","fcTypeHtml":"QBFC-IQBENTxnDisplayAddTypeType.html",
     "fcEnumValues":["tdatBill","tdatBillPayment","tdatBuildAssembly","tdatCharge","tdatCheck","tdatCreditCardCharge","tdatCreditCardCredit","tdatCreditMemo","tdatDeposit","tdatEstimate","tdatInventoryAdjustment","tdatInvoice","tdatItemReceipt","tdatJournalEntry","tdatPurchaseOrder","tdatReceivePayment","tdatSalesOrder","tdatSalesReceipt","tdatSalesTaxPaymentCheck","tdatVendorCredit"],
     "supports":{"US":true,"CA":true,"UK":true,"AU":true,"OE":true},
     "required":true,"count":"1"},
    {"xmlName":"EntityRef","xmlNameHtml":"Entity.html",
     "xmlType":"Aggregate",
     "fcName":"EntityRef","fcNameHtml":"Entity.html",
     "fcType":"IQBBaseRef",
     "minVerUS":"4",
     "supports":{"US":true,"CA":true,"UK":true,"AU":true,"OE":true},
     "required":false,"count":"0 - 1",
     "elements":[
        {"xmlName":"ListID","xmlNameHtml":"ListID.html",
         "xmlType":"IDTYPE","xmlTypeHtml":"IDTYPE.html",
         "fcName":"ListID","fcNameHtml":"ListID.html",
         "fcType":"IQBIDType","fcTypeHtml":"IQBIDType.html",
         "supports":{"US":true,"CA":true,"UK":true,"AU":true,"OE":true},
         "required":false,"count":"0 - 1"},
        {"xmlName":"FullName","xmlNameHtml":"FullName.html",
         "xmlType":"STRTYPE","xmlTypeHtml":"STRTYPE.html",
         "fcName":"FullName","fcNameHtml":"FullName.html",
         "fcType":"IQBStringType","fcTypeHtml":"IQBStringType.html",
         "maxDT":"209",
         "maxCA":"209",
         "maxUK":"209",
         "maxAU":"209",
         "maxOE":"1000",
         "supports":{"US":true,"CA":true,"UK":true,"AU":true,"OE":true},
         "required":false,"count":"0 - 1"}
     ]}
 ]}