{"xmlName":"SalesTaxReturnLineQueryRs","xmlNameHtml":"SalesTaxReturnLineQuery.html",
 "xmlType":"Aggregate",
 "fcName":"IResponse","fcNameHtml":"SalesTaxReturnLineQuery.html",
 "fcType":"nothing",
 "minVerUS":"8",
 "supports":{"US":false,"CA":true,"UK":true,"AU":true,"OE":false},
 "required":false,
 "attributes":[
    {"xmlName":"statusCode","xmlNameHtml":"statusCode.html",
     "xmlType":"INTTYPE","xmlTypeHtml":"INTTYPE.html",
     "fcName":"StatusCode","fcNameHtml":"statusCode.html",
     "fcType":"IQBIntType","fcTypeHtml":"IQBIntType.html",
     "supports":{"US":true,"CA":true,"UK":true,"AU":true,"OE":true},
     "required":true},
    {"xmlName":"statusSeverity","xmlNameHtml":"statusSeverity.html",
     "xmlType":"STRTYPE","xmlTypeHtml":"STRTYPE.html",
     "fcName":"StatusSeverity","fcNameHtml":"statusSeverity.html",
     "fcType":"IQBStringType","fcTypeHtml":"IQBStringType.html",
     "supports":{"US":true,"CA":true,"UK":true,"AU":true,"OE":true},
     "required":true},
    {"xmlName":"statusMessage","xmlNameHtml":"statusMessage.html",
     "xmlType":"STRTYPE","xmlTypeHtml":"STRTYPE.html",
     "fcName":"StatusMessage","fcNameHtml":"statusMessage.html",
     "fcType":"IQBStringType","fcTypeHtml":"IQBStringType.html",
     "supports":{"US":true,"CA":true,"UK":true,"AU":true,"OE":true},
     "required":true},
    {"xmlName":"retCount","xmlNameHtml":"retCount.html",
     "xmlType":"INTTYPE","xmlTypeHtml":"INTTYPE.html",
     "fcName":"retCount","fcNameHtml":"retCount.html",
     "fcType":"IQBIntType","fcTypeHtml":"IQBIntType.html",
     "minVerUS":"4",
     "supports":{"US":true,"CA":false,"UK":false,"AU":false,"OE":false},
     "required":false}
 ],
 "elements":[
    {"xmlName":"SalesTaxReturnLineRet","xmlNameHtml":"SalesTaxReturnLine.html",
     "xmlType":"Aggregate",
     "fcName":"Detail",
     "fcType":"ISalesTaxReturnLineRetList","fcTypeHtml":"QBFC-ISalesTaxReturnLineRetList.html",
     "fcListOf":{"fcType":"ISalesTaxReturnLineRet"},
     "supports":{"US":true,"CA":true,"UK":true,"AU":true,"OE":true},
     "required":false,"count":"0 - n",
     "elements":[
        {"xmlName":"ListID","xmlNameHtml":"ListID.html",
         "xmlType":"IDTYPE","xmlTypeHtml":"IDTYPE.html",
         "fcName":"ListID","fcNameHtml":"ListID.html",
         "fcType":"IQBIDType","fcTypeHtml":"IQBIDType.html",
         "supports":{"US":true,"CA":true,"UK":true,"AU":true,"OE":true},
         "required":true,"count":"1"},
        {"xmlName":"FullName","xmlNameHtml":"FullName.html",
         "xmlType":"STRTYPE","xmlTypeHtml":"STRTYPE.html",
         "fcName":"FullName","fcNameHtml":"FullName.html",
         "fcType":"IQBStringType","fcTypeHtml":"IQBStringType.html",
         "maxCA":"159",
         "maxUK":"159",
         "maxAU":"159",
         "supports":{"US":true,"CA":true,"UK":true,"AU":true,"OE":true},
         "required":false,"count":"0 - 1"},
        {"xmlName":"LineType","xmlNameHtml":"LineType.html",
         "xmlType":"ENUMTYPE","xmlTypeHtml":"ENUMTYPE.html",
         "xmlEnumValues":["ECPurchases","ECSales","Purchases","Sales","SubTotal","TaxOnPurchases","TaxOnSales","Total"],
         "fcName":"LineType","fcNameHtml":"QBFC-LineType.html",
         "fcType":"IQBENLineTypeType","fcTypeHtml":"QBFC-IQBENLineTypeType.html",
         "fcEnumValues":["ltECPurchases","ltECSales","ltPurchases","ltSales","ltSubTotal","ltTaxOnPurchases","ltTaxOnSales","ltTotal"],
         "supports":{"US":true,"CA":true,"UK":true,"AU":true,"OE":true},
         "required":false,"count":"0 - 1"}
     ]}
 ]}